shhell/__init__.py
shhell/command.py
shhell/executable.py
shhell/result.py
shhell/typehints.py
shhell-0.0.0.dist-info/WHEEL
shhell-0.0.0.dist-info/METADATA
shhell-0.0.0.dist-info/RECORD
