Metadata-Version: 2.1
Name: shhell
Version: 0.0.0
Summary: Subprocess replacement with fancy API to build commands, typing and, hopefully, autocompletion  support ✨
Author: Bobronium
Author-email: appkiller16@gmail.com
Requires-Python: >=3.10,<4.0
Classifier: Programming Language :: Python :: 3
Classifier: Programming Language :: Python :: 3.10
